stag/__init__.py
stag/__main__.py
stag/cleanup.py
stag/stag.py
pystag-0.2.0.dist-info/METADATA
pystag-0.2.0.dist-info/WHEEL
pystag-0.2.0.dist-info/entry_points.txt
pystag-0.2.0.dist-info/top_level.txt
pystag-0.2.0.dist-info/RECORD
