Metadata-Version: 2.1
Name: pystag
Version: 0.2.0
Summary: Tag local music using spotify api
Home-page: https://github.com/meain/stag
Author: Abin Simon
Author-email: abinsimon10@gmail.com
License: UNKNOWN
Keywords: spotify,music,tagging
Platform: UNKNOWN
Classifier: Environment :: Console
Classifier: Intended Audience :: End Users/Desktop
Classifier: Topic :: Multimedia :: Sound/Audio :: Editors
Classifier: Topic :: Software Development :: Libraries :: Python Modules
Classifier: Operating System :: POSIX
Classifier: Natural Language :: English
Classifier: Programming Language :: Python
Classifier: Programming Language :: Python :: 3.6
Classifier: Programming Language :: Python :: 3.7
Classifier: License :: OSI Approved :: MIT License
